clusterous
