Metadata-Version: 1.1
Name: clusterous
Version: 1.0.0
Summary: Clusterous is a cluster computing tool to deploy Docker containers on AWS
Home-page: https://github.com/sirca/clusterous
Author: SIRCA
Author-email: lolo.fernandez@sirca.org.au
License: UNKNOWN
Download-URL: https://github.com/sirca/clusterous/releases/download/v0.6.0/clusterous-0.6.0.tar.gz
Keywords: clusterous,docker,aws
Platform: UNKNOWN
